MagmaPandas/Elements.py
MagmaPandas/__init__.py
MagmaPandas/configuration.py
MagmaPandas/enums.py
MagmaPandas/magma_protocol.py
MagmaPandas/EOSs/CO2_H2O.py
MagmaPandas/EOSs/__init__.py
MagmaPandas/EOSs/birch_murnaghan.py
MagmaPandas/EOSs/parameters.py
MagmaPandas/EOSs/tait.py
MagmaPandas/EOSs/tools.py
MagmaPandas/EOSs/vinet.py
MagmaPandas/Fe_redox/Fe3Fe2_baseclass.py
MagmaPandas/Fe_redox/Fe3Fe2_calculate.py
MagmaPandas/Fe_redox/Fe3Fe2_errors.py
MagmaPandas/Fe_redox/Fe3Fe2_models.py
MagmaPandas/Fe_redox/__init__.py
MagmaPandas/Kd/Kd_baseclass.py
MagmaPandas/Kd/__init__.py
MagmaPandas/Kd/Ol_melt/__init__.py
MagmaPandas/Kd/Ol_melt/FeMg/Kd_calculate.py
MagmaPandas/Kd/Ol_melt/FeMg/Kd_iterate.py
MagmaPandas/Kd/Ol_melt/FeMg/Kd_models.py
MagmaPandas/Kd/Ol_melt/FeMg/__init__.py
MagmaPandas/MagmaFrames/__init__.py
MagmaPandas/MagmaFrames/clinopyroxene.py
MagmaPandas/MagmaFrames/ilmenite.py
MagmaPandas/MagmaFrames/magmaFrame.py
MagmaPandas/MagmaFrames/magnetite.py
MagmaPandas/MagmaFrames/melt.py
MagmaPandas/MagmaFrames/olivine.py
MagmaPandas/MagmaFrames/plagioclase.py
MagmaPandas/MagmaSeries/MagmaSeries_baseclass.py
MagmaPandas/MagmaSeries/__init__.py
MagmaPandas/fO2/Fe_metal.py
MagmaPandas/fO2/IW.py
MagmaPandas/fO2/NNO.py
MagmaPandas/fO2/QFM.py
MagmaPandas/fO2/RuRuO2.py
MagmaPandas/fO2/__init__ .py
MagmaPandas/fO2/fO2_calculate.py
MagmaPandas/fO2/data/IW_G0_params.csv
MagmaPandas/fO2/data/__init__.py
MagmaPandas/model_calibrations/__init__.py
MagmaPandas/model_calibrations/plot_calibration.py
MagmaPandas/model_calibrations/data/Fe3Fe2_calibration_data.csv
MagmaPandas/model_calibrations/data/Fe3Fe2_calibration_references.rtf
MagmaPandas/model_calibrations/data/Kd_calibration_data.csv
MagmaPandas/model_calibrations/data/calibration_datasets.json
MagmaPandas/parse_io/__init__.py
MagmaPandas/parse_io/parse.py
MagmaPandas/parse_io/readers.py
MagmaPandas/parse_io/validate.py
MagmaPandas/rheology/__init__.py
MagmaPandas/rheology/density.py
MagmaPandas/rheology/viscosity.py
magmapandas-2.2.6.dist-info/licenses/LICENSE
magmapandas-2.2.6.dist-info/METADATA
magmapandas-2.2.6.dist-info/WHEEL
magmapandas-2.2.6.dist-info/top_level.txt
magmapandas-2.2.6.dist-info/RECORD
