Metadata-Version: 2.4
Name: MagmaPandas
Version: 2.2.6
Summary: Pandas based tool set for geochemical processing and modelling.
Author: Thomas van Gerve
License: MIT License
Project-URL: Homepage, https://github.com/TDGerve/MagmaPandas
Classifier: Programming Language :: Python :: 3
Classifier: License :: OSI Approved :: MIT License
Classifier: Operating System :: OS Independent
Requires-Python: <3.13,>=3.10
License-File: LICENSE
Requires-Dist: pandas<=2.1.4
Requires-Dist: numpy<=1.26.4
Requires-Dist: scipy
Requires-Dist: alive_progress
Requires-Dist: matplotlib-label-lines
Requires-Dist: statsmodels
Requires-Dist: matplotlib
Requires-Dist: scikit-learn
Requires-Dist: elementMass>=1.1.0
Requires-Dist: typing_extensions
Dynamic: license-file
